compiler/compiler.py
compiler/env_data.py
compiler/environment.py
intermediate/lookup_tables.py
intermediate/tokens.py
parsing/expressions.py
parsing/parser.py
parsing/statements.py
preproccesor/env.py
preproccesor/preprocessor.py
scanning/error.py
scanning/lexer.py
venumLang-0.1.0.data/scripts/main.py
visitors/ast_printer.py
visitors/visitor.py
venumLang-0.1.0.dist-info/METADATA
venumLang-0.1.0.dist-info/WHEEL
venumLang-0.1.0.dist-info/entry_points.txt
venumLang-0.1.0.dist-info/top_level.txt
venumLang-0.1.0.dist-info/RECORD
