Metadata-Version: 2.1
Name: venumLang
Version: 0.1.0
Summary: A statically typed language written in python
Home-page: https://github.com/darealvenum/venumLang2
Author: Venumlang contributors
Platform: any
Classifier: Programming Language :: Python :: 3
Requires-Python: >=3.8
